envorbit/__init__.py
envorbit/__main__.py
envorbit/py.typed
envorbit-0.0.1.dist-info/licenses/LICENSE
envorbit-0.0.1.dist-info/METADATA
envorbit-0.0.1.dist-info/WHEEL
envorbit-0.0.1.dist-info/entry_points.txt
envorbit-0.0.1.dist-info/top_level.txt
envorbit-0.0.1.dist-info/RECORD
