Metadata-Version: 2.4
Name: envorbit
Version: 0.0.1
Summary: EnvOrbit - A future Python environment management toolkit.
Author-email: Ethan Pham <thanhtrungit2001@gmail.com>
License: MIT
Project-URL: Homepage, https://github.com/trungit2001/envorbit
Project-URL: Repository, https://github.com/trungit2001/envorbit
Project-URL: Issues, https://github.com/trungit2001/envorbit/issues
Classifier: Development Status :: 1 - Planning
Classifier: Intended Audience :: Developers
Classifier: License :: OSI Approved :: MIT License
Classifier: Programming Language :: Python :: 3
Classifier: Programming Language :: Python :: 3 :: Only
Requires-Python: >=3.12
License-File: LICENSE
Dynamic: license-file
